qci_client/__init__.py
qci_client/utilities.py
qci_client/auth/__init__.py
qci_client/auth/client.py
qci_client/auth/types.py
qci_client/optimization/__init__.py
qci_client/optimization/client.py
qci_client/optimization/data_converter.py
qci_client/optimization/enum.py
qci_client/optimization/types.py
qci_client/optimization/utilities.py
qci_client-5.0.0.dist-info/licenses/LICENSE
tests/__init__.py
tests/test_utilities.py
tests/auth/__init__.py
tests/auth/test_client.py
tests/optimization/__init__.py
tests/optimization/test_client.py
tests/optimization/test_data_converter.py
tests/optimization/test_enum.py
qci_client-5.0.0.dist-info/METADATA
qci_client-5.0.0.dist-info/WHEEL
qci_client-5.0.0.dist-info/top_level.txt
qci_client-5.0.0.dist-info/RECORD
