Metadata-Version: 2.4
Name: qci-client
Version: 5.0.0
Summary: Client Package for using Qatalyst Optimization Suite
Author-email: "Quantum Computing Inc." <support@quantumcomputinginc.com>
License: Apache 2.0
Project-URL: documentation, https://quantumcomputinginc.com/learn/developer-resources/entropy-quantum-optimization/qci-client-software-package/latest/qci-client
Classifier: License :: OSI Approved :: Apache Software License
Classifier: Programming Language :: Python
Classifier: Programming Language :: Python :: 3
Requires-Python: <3.14,>=3.9
License-File: LICENSE
Requires-Dist: requests<3,>=2.22.1
Requires-Dist: requests-futures<2,>=1.0.0
Requires-Dist: networkx<3,>=2.6.3
Requires-Dist: numpy<3,>=1.21.1
Requires-Dist: scipy<2,>=1.7.3
Provides-Extra: dev
Requires-Dist: black<25,>=24.3.0; extra == "dev"
Requires-Dist: build<2,>=1.2.2.post1; extra == "dev"
Requires-Dist: check-manifest<0.51,>=0.50; extra == "dev"
Requires-Dist: coverage[toml]<7,>=6.4.2; extra == "dev"
Requires-Dist: pylint<4,>=3.1.0; extra == "dev"
Requires-Dist: pytest<8,>=7.2.1; extra == "dev"
Requires-Dist: sphinx-rtd-theme<2,>=1.3.0; extra == "dev"
Requires-Dist: tomli<3,>=2.2.1; extra == "dev"
Dynamic: license-file
